Topsis/__init__.py
Topsis/__main__.py
Topsis_Mohak_102103144-1.1.2.dist-info/METADATA
Topsis_Mohak_102103144-1.1.2.dist-info/WHEEL
Topsis_Mohak_102103144-1.1.2.dist-info/entry_points.txt
Topsis_Mohak_102103144-1.1.2.dist-info/top_level.txt
Topsis_Mohak_102103144-1.1.2.dist-info/RECORD
