Metadata-Version: 2.1
Name: Topsis-Mohak-102103144
Version: 1.1.2
Author: Mohak Singh
License: MIT
Classifier: License :: OSI Approved :: MIT License
Classifier: Programming Language :: Python :: 3.6
Classifier: Programming Language :: Python :: 3.7
Classifier: Programming Language :: Python :: 3.8
Requires-Dist: numpy
Requires-Dist: pandas
